MANIFEST.in
setup.cfg
setup.py
cozy_fuse.egg-info/PKG-INFO
cozy_fuse.egg-info/SOURCES.txt
cozy_fuse.egg-info/dependency_links.txt
cozy_fuse.egg-info/entry_points.txt
cozy_fuse.egg-info/not-zip-safe
cozy_fuse.egg-info/requires.txt
cozy_fuse.egg-info/top_level.txt
cozyfuse/__init__.py
cozyfuse/__main__.py
cozyfuse/actions.py
cozyfuse/binary.py
cozyfuse/compil.py
cozyfuse/config.py
cozyfuse/couchmount.py
cozyfuse/cozy_fuse.py
cozyfuse/dbutils.py
cozyfuse/end.py
cozyfuse/install.py
cozyfuse/local_config.py
cozyfuse/remote.py
cozyfuse/replication.py
test/test.py