Metadata-Version: 1.1
Name: cozy-fuse
Version: 0.1.2
Summary: FUSE implementation for Cozy Files
Home-page: https://github.com/cozy/cozy-fuse
Author: Cozy Cloud
Author-email: contact@cozycloud.cc
License: LGPL
Download-URL: https://github.com/cozy/cozy-fuse/tarball/0.1.2
Keywords: cozy,fuse,linux,osx
Platform: UNKNOWN
Classifier: Development Status :: 3 - Alpha
Classifier: Environment :: Console
Classifier: License :: OSI Approved :: GNU Library or Lesser General Public License (LGPL)
Classifier: Operating System :: Unix
Classifier: Operating System :: POSIX
Classifier: Programming Language :: Python
Classifier: Programming Language :: Python :: 2.5
Classifier: Programming Language :: Python :: 2.6
Classifier: Programming Language :: Python :: 2.7
Classifier: Topic :: System :: Software Distribution
Classifier: Topic :: System :: Systems Administration
